code_structure_tools/__init__.py
code_structure_tools/class_utils.py
code_structure_tools/cython_utils.py
code_structure_tools/decorators.py
code_structure_tools/dunder_utils.py
code_structure_tools/function_utils.py
code_structure_tools/functools_utils.py
code_structure_tools/inheritance_utils.py
code_structure_tools/metaclass_utils.py
code_structure_tools/module_class_transition_example.py
code_structure_tools/module_utils.py
code_structure_tools/namespace_utils.py
code_structure_tools/object_utils.py
code_structure_tools/test_decorators.py
code_structure_tools/transitions.py
code_structure_tools-1.0.2.dist-info/DESCRIPTION.rst
code_structure_tools-1.0.2.dist-info/METADATA
code_structure_tools-1.0.2.dist-info/RECORD
code_structure_tools-1.0.2.dist-info/WHEEL
code_structure_tools-1.0.2.dist-info/metadata.json
code_structure_tools-1.0.2.dist-info/top_level.txt
